{
    "id": 135438759,
    "name": "KiuiIsLate Superbuffed",
    "author": "LaserStr",
    "creators": [],
    "verifier": "LaserStr",
    "verification": "https://youtu.be/V2VGJeOeHrk",
    "percentToQualify": 100,
    "records": [
        {
            "user": "Shialaxy",
            "link": "https://youtu.be/Ii5NUbuci4U",
            "percent": 100,
            "hz": 240
        },
        {
            "user": "Helios-YT-1",
            "link": "https://youtube.com/shorts/yC3gSrfBLyw?si=FVT3IBEQzhLw-NBZ",
            "percent": 100,
            "hz": 60
        },
        {
            "user": "Zodiac",
            "link": "https://drive.google.com/file/d/1es2brQ7FhF8PNa4SICvOVXGH3vaccNBq/view?usp=sharing",
            "percent": 100,
            "hz": 240
        },
        {
            "user": "DD",
            "link": "https://youtu.be/omvJl_f_HYI",
            "percent": 100,
            "hz": 240
        }
    ]
}
